MCP.py
innaguma_mcp-0.0.12.dist-info/METADATA
innaguma_mcp-0.0.12.dist-info/WHEEL
innaguma_mcp-0.0.12.dist-info/entry_points.txt
innaguma_mcp-0.0.12.dist-info/top_level.txt
innaguma_mcp-0.0.12.dist-info/RECORD
