Metadata-Version: 2.4
Name: innaguma-mcp
Version: 0.0.12
Summary: Innaguma MCP Server - Analytics and content management integration with FastMCP
Author-email: Bruno Izaguirre <bruno.izaguirre@ingeteam.com>
Requires-Python: >=3.10
Requires-Dist: fastmcp<3.0.0,>=2.13.0
Requires-Dist: aiohttp>=3.9.0
Requires-Dist: python-dotenv>=1.0.0
Requires-Dist: pyjwt>=2.8.0
Requires-Dist: beautifulsoup4>=4.12.0
Requires-Dist: lxml>=4.9.0
